[
    {
        "name": "G. Oliveira",
        "team_match": "BEN - RMA",
        "position": "DEF",
        "price": "4m",
        "ptos_total": "0",
        "seleccionado": "0",
        "ptos_jornada": "0",
        "ptos_por_euro": "0",
        "ptos_per_md": "0",
        "ptos_potm": "0",
        "goles": "0",
        "asistencias": "0",
        "balones_recuperados": "0",
        "porteria_a_0": "0",
        "tarjetas_rojas": "0",
        "tarjetas_amarillas": "0",
        "mins_jugados": "0",
        "fichados": "24",
        "prox_partido": "RMA (H)",
        "estado_forma": "0.0 stars"
    },
    {
        "name": "Nuno Mendes",
        "team_match": "MON - PSG",
        "position": "DEF",
        "price": "6.3m",
        "ptos_total": "57",
        "seleccionado": "50 %",
        "ptos_jornada": "4",
        "ptos_por_euro": "9.1",
        "ptos_per_md": "7.1",
        "ptos_potm": "6",
        "goles": "2",
        "asistencias": "2",
        "balones_recuperados": "57",
        "porteria_a_0": "2",
        "tarjetas_rojas": "0",
        "tarjetas_amarillas": "2",
        "mins_jugados": "660",
        "fichados": "27947",
        "prox_partido": "MON (A)",
        "estado_forma": "4.5 stars"
    },
    {
        "name": "C. Mawissa",
        "team_match": "MON - PSG",
        "position": "DEF",
        "price": "3.8m",
        "ptos_total": "1",
        "seleccionado": "0",
        "ptos_jornada": "0",
        "ptos_por_euro": "0.3",
        "ptos_per_md": "0.5",
        "ptos_potm": "0",
        "goles": "0",
        "asistencias": "0",
        "balones_recuperados": "5",
        "porteria_a_0": "0",
        "tarjetas_rojas": "0",
        "tarjetas_amarillas": "1",
        "mins_jugados": "98",
        "fichados": "11",
        "prox_partido": "PSG (H)",
        "estado_forma": "0.0 stars"
    },
    {
        "name": "G. Prestianni",
        "team_match": "BEN - RMA",
        "position": "DEL",
        "price": "4.7m",
        "ptos_total": "6",
        "seleccionado": "0",
        "ptos_jornada": "2",
        "ptos_por_euro": "1.3",
        "ptos_per_md": "1.5",
        "ptos_potm": "0",
        "goles": "0",
        "asistencias": "0",
        "balones_recuperados": "7",
        "porteria_a_0": "0",
        "tarjetas_rojas": "0",
        "tarjetas_amarillas": "0",
        "mins_jugados": "206",
        "fichados": "66",
        "prox_partido": "RMA (H)",
        "estado_forma": "1.0 stars"
    },
    {
        "name": "R. Sallai",
        "team_match": "GAL - JUV",
        "position": "CEN",
        "price": "5m",
        "ptos_total": "26",
        "seleccionado": "0",
        "ptos_jornada": "3",
        "ptos_por_euro": "5.2",
        "ptos_per_md": "3.3",
        "ptos_potm": "0",
        "goles": "0",
        "asistencias": "1",
        "balones_recuperados": "30",
        "porteria_a_0": "1",
        "tarjetas_rojas": "0",
        "tarjetas_amarillas": "1",
        "mins_jugados": "649",
        "fichados": "57",
        "prox_partido": "JUV (H)",
        "estado_forma": "3.5 stars"
    },
    {
        "name": "A. Liatsikouras",
        "team_match": "OLY - LEV",
        "position": "CEN",
        "price": "5m",
        "ptos_total": "0",
        "seleccionado": "0",
        "ptos_jornada": "0",
        "ptos_por_euro": "0",
        "ptos_per_md": "0",
        "ptos_potm": "0",
        "goles": "0",
        "asistencias": "0",
        "balones_recuperados": "0",
        "porteria_a_0": "0",
        "tarjetas_rojas": "0",
        "tarjetas_amarillas": "0",
        "mins_jugados": "0",
        "fichados": "4",
        "prox_partido": "LEV (H)",
        "estado_forma": "0.0 stars"
    },
    {
        "name": "M. Diakhon",
        "team_match": "BRU - ATM",
        "position": "DEL",
        "price": "4.6m",
        "ptos_total": "22",
        "seleccionado": "0",
        "ptos_jornada": "6",
        "ptos_por_euro": "4.8",
        "ptos_per_md": "3.1",
        "ptos_potm": "3",
        "goles": "2",
        "asistencias": "1",
        "balones_recuperados": "0",
        "porteria_a_0": "0",
        "tarjetas_rojas": "0",
        "tarjetas_amarillas": "1",
        "mins_jugados": "235",
        "fichados": "180",
        "prox_partido": "ATM (H)",
        "estado_forma": "3.5 stars"
    },
    {
        "name": "Nuno Félix",
        "team_match": "BEN - RMA",
        "position": "CEN",
        "price": "4.5m",
        "ptos_total": "0",
        "seleccionado": "0",
        "ptos_jornada": "0",
        "ptos_por_euro": "0",
        "ptos_per_md": "0",
        "ptos_potm": "0",
        "goles": "0",
        "asistencias": "0",
        "balones_recuperados": "0",
        "porteria_a_0": "0",
        "tarjetas_rojas": "0",
        "tarjetas_amarillas": "0",
        "mins_jugados": "0",
        "fichados": "22",
        "prox_partido": "RMA (H)",
        "estado_forma": "0.0 stars"
    },
    {
        "name": "N. Mensah",
        "team_match": "OLY - LEV",
        "position": "CEN",
        "price": "4.5m",
        "ptos_total": "0",
        "seleccionado": "0",
        "ptos_jornada": "0",
        "ptos_por_euro": "0",
        "ptos_per_md": "0",
        "ptos_potm": "0",
        "goles": "0",
        "asistencias": "0",
        "balones_recuperados": "0",
        "porteria_a_0": "0",
        "tarjetas_rojas": "0",
        "tarjetas_amarillas": "0",
        "mins_jugados": "0",
        "fichados": "21",
        "prox_partido": "OLY (A)",
        "estado_forma": "0.0 stars"
    },
    {
        "name": "L. Bergvall",
        "team_match": "TOT",
        "position": "CEN",
        "price": "5.1m",
        "ptos_total": "21",
        "seleccionado": "1 %",
        "ptos_jornada": "0",
        "ptos_por_euro": "4.1",
        "ptos_per_md": "3.5",
        "ptos_potm": "3",
        "goles": "0",
        "asistencias": "1",
        "balones_recuperados": "13",
        "porteria_a_0": "3",
        "tarjetas_rojas": "0",
        "tarjetas_amarillas": "1",
        "mins_jugados": "361",
        "fichados": "4",
        "prox_partido": "-",
        "estado_forma": "0.0 stars"
    },
    {
        "name": "L. Samardžić",
        "team_match": "BVB - ATA",
        "position": "CEN",
        "price": "5m",
        "ptos_total": "20",
        "seleccionado": "0",
        "ptos_jornada": "0",
        "ptos_por_euro": "4",
        "ptos_per_md": "3.3",
        "ptos_potm": "3",
        "goles": "2",
        "asistencias": "0",
        "balones_recuperados": "4",
        "porteria_a_0": "0",
        "tarjetas_rojas": "0",
        "tarjetas_amarillas": "1",
        "mins_jugados": "147",
        "fichados": "28",
        "prox_partido": "BVB (A)",
        "estado_forma": "0.5 stars"
    },
    {
        "name": "S. Auklend",
        "team_match": "BOD - INT",
        "position": "CEN",
        "price": "4.5m",
        "ptos_total": "13",
        "seleccionado": "0",
        "ptos_jornada": "1",
        "ptos_por_euro": "2.9",
        "ptos_per_md": "1.9",
        "ptos_potm": "0",
        "goles": "0",
        "asistencias": "0",
        "balones_recuperados": "11",
        "porteria_a_0": "0",
        "tarjetas_rojas": "0",
        "tarjetas_amarillas": "2",
        "mins_jugados": "393",
        "fichados": "10",
        "prox_partido": "INT (H)",
        "estado_forma": "0.0 stars"
    },
    {
        "name": "N. Botis",
        "team_match": "OLY - LEV",
        "position": "POR",
        "price": "4m",
        "ptos_total": "0",
        "seleccionado": "0",
        "ptos_jornada": "0",
        "ptos_por_euro": "0",
        "ptos_per_md": "0",
        "ptos_potm": "0",
        "goles": "0",
        "asistencias": "0",
        "balones_recuperados": "0",
        "porteria_a_0": "0",
        "tarjetas_rojas": "0",
        "tarjetas_amarillas": "0",
        "mins_jugados": "0",
        "fichados": "30",
        "prox_partido": "LEV (H)",
        "estado_forma": "0.0 stars"
    },
    {
        "name": "L. Colwill",
        "team_match": "CHE",
        "position": "DEF",
        "price": "5m",
        "ptos_total": "0",
        "seleccionado": "0",
        "ptos_jornada": "0",
        "ptos_por_euro": "0",
        "ptos_per_md": "0",
        "ptos_potm": "0",
        "goles": "0",
        "asistencias": "0",
        "balones_recuperados": "0",
        "porteria_a_0": "0",
        "tarjetas_rojas": "0",
        "tarjetas_amarillas": "0",
        "mins_jugados": "0",
        "fichados": "15",
        "prox_partido": "-",
        "estado_forma": "0.0 stars"
    },
    {
        "name": "W. McKennie",
        "team_match": "GAL - JUV",
        "position": "CEN",
        "price": "6.1m",
        "ptos_total": "39",
        "seleccionado": "1 %",
        "ptos_jornada": "5",
        "ptos_por_euro": "6.4",
        "ptos_per_md": "4.9",
        "ptos_potm": "0",
        "goles": "3",
        "asistencias": "0",
        "balones_recuperados": "28",
        "porteria_a_0": "3",
        "tarjetas_rojas": "0",
        "tarjetas_amarillas": "1",
        "mins_jugados": "689",
        "fichados": "2776",
        "prox_partido": "GAL (A)",
        "estado_forma": "4.0 stars"
    }
]